wsp_tools/__init__.py
wsp_tools/beam.py
wsp_tools/cielab.py
wsp_tools/constants.py
wsp_tools/image_processing.py
wsp_tools/lorentzSim.py
wsp_tools/ltem.py
wsp_tools/pyplotwrapper.py
wsp_tools/sitie.py
wsp_tools-1.4.1.dist-info/LICENSE
wsp_tools-1.4.1.dist-info/METADATA
wsp_tools-1.4.1.dist-info/WHEEL
wsp_tools-1.4.1.dist-info/top_level.txt
wsp_tools-1.4.1.dist-info/RECORD
