Metadata-Version: 2.1
Name: wsp-tools
Version: 1.4.1
Summary: Utilities for TEM data analysis and simulation.
Home-page: https://github.com/McMorranLab/wsp_tools
Author: William S. Parker
Author-email: wparker4@uoregon.edu
License: UNKNOWN
Project-URL: Documentation, https://mcmorranlab.github.io/wsp_tools/
Project-URL: Bug Tracker, https://github.com/McMorranLab/wsp_tools/issues
Platform: UNKNOWN
Classifier: Programming Language :: Python :: 3
Classifier: License :: OSI Approved :: GNU General Public License v3 (GPLv3)
Classifier: Operating System :: OS Independent
Requires-Python: >=3.6
License-File: LICENSE
Requires-Dist: numpy
Requires-Dist: matplotlib
Requires-Dist: scipy
Requires-Dist: pdoc3
Requires-Dist: deprecated
